gradattack/__init__.py
gradattack/datamodules.py
gradattack/trainingpipeline.py
gradattack/utils.py
gradattack/attacks/__init__.py
gradattack/attacks/attack.py
gradattack/attacks/gradientinversion.py
gradattack/defenses/__init__.py
gradattack/defenses/defense.py
gradattack/defenses/defense_utils.py
gradattack/defenses/dpsgd.py
gradattack/defenses/gradprune.py
gradattack/defenses/instahide.py
gradattack/defenses/mixup.py
gradattack/metrics/__init__.py
gradattack/metrics/gradients.py
gradattack/metrics/pixelwise.py
gradattack/models/LeNet.py
gradattack/models/__init__.py
gradattack/models/alldnet.py
gradattack/models/covidmodel.py
gradattack/models/densenet.py
gradattack/models/googlenet.py
gradattack/models/mobilenet.py
gradattack/models/multihead_resnet.py
gradattack/models/nasnet.py
gradattack/models/resnet.py
gradattack/models/resnext.py
gradattack/models/simple.py
gradattack/models/vgg.py
test/__init__.py
test/test_attack.py
test/test_defenses.py
test/test_pipeline.py
test/train_config.py
test/utils.py
GradAttack-0.1.2.dist-info/LICENSE
GradAttack-0.1.2.dist-info/METADATA
GradAttack-0.1.2.dist-info/WHEEL
GradAttack-0.1.2.dist-info/top_level.txt
GradAttack-0.1.2.dist-info/RECORD
