Metadata-Version: 2.1
Name: GradAttack
Version: 0.1.2
Summary: A small example package
Home-page: https://github.com/Princeton-SysML/GradAttack
Author: "Yangsibo Huang <yangsibo@princeton.edu>, Samyak Gupta <samyakg@princeton.edu"
Author-email: "samyakg@princeton.edu"
License: UNKNOWN
Project-URL: Bug Tracker, https://github.com/Princeton-SysML/GradAttack/issues
Platform: UNKNOWN
Classifier: Programming Language :: Python :: 3
Classifier: License :: OSI Approved :: MIT License
Classifier: Operating System :: OS Independent
Requires-Python: >=3.8
License-File: LICENSE
Requires-Dist: colorama (==0.4.4)
Requires-Dist: matplotlib (==3.4.3)
Requires-Dist: numpy (==1.21.4)
Requires-Dist: opacus (==0.14.0)
Requires-Dist: pytorch-lightning (==1.3.1)
Requires-Dist: scikit-learn (==1.0.1)
Requires-Dist: torch (==1.8.1)
Requires-Dist: torchcsprng (==0.2.1)
Requires-Dist: torchmetrics (==0.6.0)
Requires-Dist: torchvision (==0.9.1)
